PekatVisionSDK/__about__.py
PekatVisionSDK/__init__.py
PekatVisionSDK/errors.py
PekatVisionSDK/instance.py
PekatVisionSDK/result.py
pekat_vision_sdk-2.3.2.dist-info/METADATA
pekat_vision_sdk-2.3.2.dist-info/WHEEL
pekat_vision_sdk-2.3.2.dist-info/licenses/LICENSE
pekat_vision_sdk-2.3.2.dist-info/RECORD
