Metadata-Version: 2.4
Name: pekat-vision-sdk
Version: 2.3.2
Summary: A Python module for communication with PEKAT VISION
Project-URL: Homepage, https://github.com/pekat-vision/pekat-vision-sdk-python
Project-URL: Documentation, https://pekat-vision.github.io/pekat-vision-sdk-python/
Project-URL: Repository, https://github.com/pekat-vision/pekat-vision-sdk-python.git
Project-URL: Changelog, https://github.com/pekat-vision/pekat-vision-sdk-python/blob/master/CHANGELOG.md
Author-email: developers@pekatvision.com
Maintainer-email: developers@pekatvision.com
License-Expression: MIT
License-File: LICENSE
Keywords: pekat,pekatvision,pekatvisionsdk,sdk,vision
Classifier: Development Status :: 5 - Production/Stable
Classifier: License :: OSI Approved :: MIT License
Classifier: Programming Language :: Python :: 3
Classifier: Programming Language :: Python :: 3 :: Only
Classifier: Programming Language :: Python :: 3.8
Requires-Python: >=3.8
Requires-Dist: netifaces2
Requires-Dist: numpy
Requires-Dist: packaging
Requires-Dist: requests
Provides-Extra: opencv
Requires-Dist: opencv-python; extra == 'opencv'
